LICENSE.txt
MANIFEST.in
README.md
setup.py
tdl-CHANGELOG.txt
tdl-README.txt
docs/api-objects.txt
docs/class-tree.html
docs/crarr.png
docs/epydoc-log.html
docs/epydoc.config
docs/epydoc.css
docs/epydoc.js
docs/frames.html
docs/help.html
docs/identifier-index.html
docs/index.html
docs/module-tree.html
docs/redirect.html
docs/toc-everything.html
docs/toc-untdl-module.html
docs/toc-untdl.event-module.html
docs/toc-untdl.map-module.html
docs/toc-untdl.noise-module.html
docs/toc.html
docs/untdl-module.html
docs/untdl-pysrc.html
docs/untdl.Console-class.html
docs/untdl.TDLError-class.html
docs/untdl.Window-class.html
docs/untdl._MetaConsole-class.html
docs/untdl.event-module.html
docs/untdl.event-pysrc.html
docs/untdl.event.App-class.html
docs/untdl.event.Event-class.html
docs/untdl.event.KeyDown-class.html
docs/untdl.event.KeyEvent-class.html
docs/untdl.event.KeyUp-class.html
docs/untdl.event.MouseButtonEvent-class.html
docs/untdl.event.MouseDown-class.html
docs/untdl.event.MouseMotion-class.html
docs/untdl.event.MouseUp-class.html
docs/untdl.event.Quit-class.html
docs/untdl.map-module.html
docs/untdl.map-pysrc.html
docs/untdl.map.AStar-class.html
docs/untdl.noise-module.html
docs/untdl.noise-pysrc.html
docs/untdl.noise.Noise-class.html
examples/eventget.py
examples/helloWorld.py
examples/interactive.py
fonts/X11/10x20.png
fonts/X11/4x6.png
fonts/X11/5x7.png
fonts/X11/5x8.png
fonts/X11/6x10.png
fonts/X11/6x12.png
fonts/X11/6x13.png
fonts/X11/6x13B.png
fonts/X11/6x13O.png
fonts/X11/6x9.png
fonts/X11/7x13.png
fonts/X11/7x13B.png
fonts/X11/7x13O.png
fonts/X11/7x14.png
fonts/X11/7x14B.png
fonts/X11/8x13.png
fonts/X11/8x13B.png
fonts/X11/8x13O.png
fonts/X11/9x15.png
fonts/X11/9x15B.png
fonts/X11/9x18.png
fonts/X11/9x18B.png
fonts/X11/AUTHORS.txt
fonts/X11/LICENCES.txt
fonts/X11/README-TDL.txt
fonts/X11/README-X11.txt
fonts/X11/TARGET1.txt
fonts/X11/TARGET2.txt
fonts/X11/TARGET3.txt
fonts/X11/clR6x12.png
fonts/X11/helvR12_14x15.png
fonts/X11/unifont-16x16.png
untdl.egg-info/PKG-INFO
untdl.egg-info/SOURCES.txt
untdl.egg-info/dependency_links.txt
untdl.egg-info/top_level.txt
