Metadata-Version: 1.1
Name: untdl
Version: 0.2.1
Summary: Fork of tdl (Pythonic port of rogue-like library libtcod).
Home-page: https://github.com/leecannon/untdl
Author: Lee Cannon
Author-email: leecannon.siy@gmail.com
License: New BSD License
Download-URL: https://github.com/leecannon/untdl
Keywords: portable rogue-like rogue-likes text ctypes ASCII ANSI Unicode libtcod fov
Platform: Windows
Platform: Mac OS X
Platform: Linux
Classifier: Development Status :: 5 - Production/Stable
Classifier: Environment :: Win32 (MS Windows)
Classifier: Environment :: MacOS X
Classifier: Environment :: X11 Applications
Classifier: Intended Audience :: Developers
Classifier: License :: OSI Approved :: BSD License
Classifier: Natural Language :: English
Classifier: Operating System :: POSIX
Classifier: Operating System :: MacOS
Classifier: Operating System :: Microsoft :: Windows
Classifier: Programming Language :: Python :: 2.6
Classifier: Programming Language :: Python :: 2.7
Classifier: Programming Language :: Python :: 3
Classifier: Programming Language :: Python :: 3.0
Classifier: Programming Language :: Python :: 3.1
Classifier: Programming Language :: Python :: 3.2
Classifier: Programming Language :: Python :: 3.3
Classifier: Programming Language :: Python :: 3.4
Classifier: Programming Language :: Python :: Implementation :: CPython
Classifier: Programming Language :: Python :: Implementation :: PyPy
Classifier: Topic :: Games/Entertainment
Classifier: Topic :: Multimedia :: Graphics
Classifier: Topic :: Software Development :: Libraries :: Python Modules
